LICENSE
MANIFEST.in
README.rst
setup.py
psycopg2cffi/__init__.py
psycopg2cffi/_json.py
psycopg2cffi/_range.py
psycopg2cffi/compat.py
psycopg2cffi/errorcodes.py
psycopg2cffi/extensions.py
psycopg2cffi/extras.py
psycopg2cffi/pool.py
psycopg2cffi/psycopg1.py
psycopg2cffi/tz.py
psycopg2cffi.egg-info/PKG-INFO
psycopg2cffi.egg-info/SOURCES.txt
psycopg2cffi.egg-info/dependency_links.txt
psycopg2cffi.egg-info/requires.txt
psycopg2cffi.egg-info/top_level.txt
psycopg2cffi/_impl/__init__.py
psycopg2cffi/_impl/_build_libpq.py
psycopg2cffi/_impl/adapters.py
psycopg2cffi/_impl/connection.py
psycopg2cffi/_impl/consts.py
psycopg2cffi/_impl/cursor.py
psycopg2cffi/_impl/encodings.py
psycopg2cffi/_impl/exceptions.py
psycopg2cffi/_impl/libpq.py
psycopg2cffi/_impl/lobject.py
psycopg2cffi/_impl/notify.py
psycopg2cffi/_impl/typecasts.py
psycopg2cffi/_impl/util.py
psycopg2cffi/_impl/xid.py
psycopg2cffi/tests/__init__.py
psycopg2cffi/tests/test_errorcodes.py
psycopg2cffi/tests/test_extensions.py
psycopg2cffi/tests/test_notify.py