Metadata-Version: 1.1
Name: psycopg2cffi
Version: 2.7.5
Summary: .. image:: https://travis-ci.org/chtd/psycopg2cffi.svg?branch=master
Home-page: http://github.com/chtd/psycopg2cffi
Author: Konstantin Lopuhin
Author-email: konstantin.lopuhin@chtd.ru
License: LGPL
Platform: any
Classifier: Development Status :: 3 - Alpha
Classifier: License :: OSI Approved :: GNU Library or Lesser General Public License (LGPL)
Classifier: Intended Audience :: Developers
Classifier: Programming Language :: Python :: 2.6
Classifier: Programming Language :: Python :: 2.7
Classifier: Programming Language :: Python :: 3.2
Classifier: Programming Language :: Python :: 3.3
Classifier: Programming Language :: Python :: 3.4
Classifier: Programming Language :: Python :: Implementation :: CPython
Classifier: Programming Language :: Python :: Implementation :: PyPy
Classifier: Programming Language :: SQL
Classifier: Topic :: Database
Classifier: Topic :: Database :: Front-Ends
